mp3.pypy39-pp73-win_amd64.pyd
pymp3-0.2.0.dist-info/LICENSE
pymp3-0.2.0.dist-info/METADATA
pymp3-0.2.0.dist-info/WHEEL
pymp3-0.2.0.dist-info/top_level.txt
pymp3-0.2.0.dist-info/RECORD
