Metadata-Version: 2.1
Name: pymp3
Version: 0.2.0
Summary: Read and write MP3 files.
Home-page: https://github.com/miarec/pymp3
Author: Gennadiy Bezkorovayniy
Author-email: gb@miarec.com
License: GPL
Platform: UNKNOWN
Classifier: Topic :: Multimedia :: Sound/Audio :: Conversion
Classifier: Programming Language :: Python :: 3 :: Only
Classifier: License :: OSI Approved :: GNU General Public License v2 (GPLv2)
Classifier: Operating System :: Microsoft :: Windows
Classifier: Operating System :: POSIX :: Linux
Requires-Python: >=3.6
License-File: LICENSE
